openrelik_api_client/__init__.py
openrelik_api_client/api_client.py
openrelik_api_client-2024.10.3.dist-info/LICENSE
openrelik_api_client-2024.10.3.dist-info/METADATA
openrelik_api_client-2024.10.3.dist-info/WHEEL
openrelik_api_client-2024.10.3.dist-info/RECORD
