Metadata-Version: 2.1
Name: openrelik-api-client
Version: 2024.10.3
Summary: API client that automatically handles token refresh
Author: Johan Berggren
Author-email: jberggren@gmail.com
Requires-Python: >=3.10,<4.0
Classifier: Programming Language :: Python :: 3
Classifier: Programming Language :: Python :: 3.10
Classifier: Programming Language :: Python :: 3.11
Classifier: Programming Language :: Python :: 3.12
Requires-Dist: requests (>=2.32.3,<3.0.0)
